README.md
setup.py
standup_host/__init__.py
standup_host/__main__.py
standup_host/config.py
standup_host.egg-info/PKG-INFO
standup_host.egg-info/SOURCES.txt
standup_host.egg-info/dependency_links.txt
standup_host.egg-info/entry_points.txt
standup_host.egg-info/requires.txt
standup_host.egg-info/top_level.txt