Metadata-Version: 2.1
Name: standup-host
Version: 0.0.1
Summary: Host an effective standup.
Home-page: https://github.com/agrana/standup_host/
Author: agrana
Author-email: alfonso.grana@gmail.com
License: MIT
Platform: UNKNOWN
Classifier: License :: OSI Approved :: MIT License
Classifier: Programming Language :: Python :: 3
Classifier: Programming Language :: Python :: 3.7
